{
	"_id": "abandoned_oiquqo.nutrient_filter",
	"type": "fragment",
	"mode": "npc",
	"script": "abandoned_oiquqo.nutrient_filter",
	"sector": "SPC_4577",
	"sec_level": 4,
	"date_added": 1659055594064,
	"last_scraped": 1664432115605,
	"script_log": [
		{
			"type": "added",
			"when": 1659055594064
		}
	],
	"next_scrape": 1664476753349,
	"category": "dice_roller",
	"last_update": 1664432115605,
	"output": [
		{
			"args": {},
			"calls": 2688106,
			"base": "Roll the dice!(tm)\n\nbeat the house's roll to win! {roll:true}",
			"fragments": [
				"quipm",
				"emplo",
				"; cre",
				"ronmen",
				"on of ",
				"of com",
				"ibited",
				"enalti",
				"sets; i",
				"se of c",
				"oyment;",
				"mmary o",
				"ion equ",
				"ent; cr",
				"eation ",
				"s; inapp",
				"S mainte",
				"ited dig",
				"creation",
				" to secu"
			],
			"hits": [
				{
					"document": "MFT0XC3_CLST0XC4_SECT0X085A_FILE0X64C10251",
					"frags": [
						"quipm",
						"ronmen",
						"mmary o",
						"ited dig",
						"creation"
					]
				}
			]
		}
	],
	"identified": [
		{
			"document": "MFT0XC3_CLST0XC4_SECT0X085A_FILE0X64C10251",
			"frags": [
				"quipm",
				"ronmen",
				"mmary o",
				"ited dig",
				"creation"
			]
		}
	],
	"updt": 1664424927319,
	"edit": 639
}