{
	"_id": "abndnd_xcwg4p.base",
	"type": "fragment",
	"mode": "dead",
	"script": "abndnd_xcwg4p.base",
	"sector": "NGC_3338",
	"sec_level": 2,
	"date_added": 1608336951983,
	"last_scraped": 1609952215309,
	"script_log": [
		{
			"type": "added",
			"when": 1608336951983
		},
		{
			"type": "died",
			"when": 1614256327150
		},
		{
			"type": "died",
			"when": 1617291633650
		},
		{
			"type": "died",
			"when": 1622510985114
		},
		{
			"type": "died",
			"when": 1622511007796
		},
		{
			"type": "died",
			"when": 1625436508927
		},
		{
			"type": "died",
			"when": 1627098914976
		},
		{
			"type": "died",
			"when": 1629239163664
		},
		{
			"type": "died",
			"when": 1629239172401
		},
		{
			"type": "died",
			"when": 1629239189589
		},
		{
			"type": "died",
			"when": 1629239233827
		},
		{
			"type": "died",
			"when": 1629239243798
		},
		{
			"type": "died",
			"when": 1629255737889
		},
		{
			"type": "died",
			"when": 1629255751398
		},
		{
			"type": "died",
			"when": 1629255762814
		},
		{
			"type": "died",
			"when": 1629255824248
		},
		{
			"type": "died",
			"when": 1629255833911
		}
	],
	"updt": 1629293107422,
	"edit": 14,
	"next_scrape": 1610035308112,
	"category": "UNKNOWN CATEGORY",
	"last_update": 1609952215309,
	"output": [
		{
			"args": {},
			"calls": 18620,
			"base": "\"ah. ye again.\nmy ol bones need a rest from extortion. ye come back termorrow.\"\n--the upkeeper",
			"fragments": [
				"ting ",
				"comme",
				" and ",
				"(video",
				"onstruc",
				"anic' o",
				"ncidenta",
				"itorial ",
				"ic' or '",
				"cial wri",
				"al' form"
			],
			"hits": [
				{
					"document": "MFT0X71_CLST0X8A_SECT0X7356_FILE0X14AFF93F",
					"frags": [
						"ting ",
						"comme",
						" and ",
						"(video",
						"onstruc",
						"anic' o",
						"ncidenta",
						"itorial ",
						"ic' or '",
						"cial wri",
						"al' form"
					]
				}
			]
		}
	],
	"identified": [
		{
			"document": "MFT0X71_CLST0X8A_SECT0X7356_FILE0X14AFF93F",
			"frags": [
				"ting ",
				"comme",
				" and ",
				"(video",
				"onstruc",
				"anic' o",
				"ncidenta",
				"itorial ",
				"ic' or '",
				"cial wri",
				"al' form"
			]
		}
	]
}