{
	"_id": "abndnd_uy7llh.bot_scam_do_not_run",
	"type": "fragment",
	"mode": "player",
	"script": "abndnd_uy7llh.bot_scam_do_not_run",
	"sector": "K_3215",
	"sec_level": 4,
	"date_added": 1624090776116,
	"last_scraped": 1631792492384,
	"script_log": [
		{
			"type": "added",
			"when": 1624090776116
		},
		{
			"type": "died",
			"when": 1631758775688
		},
		{
			"type": "died",
			"when": 1631764319192
		},
		{
			"type": "died",
			"when": 1631769896472
		},
		{
			"type": "died",
			"when": 1631775431449
		},
		{
			"type": "died",
			"when": 1631781316375
		},
		{
			"type": "died",
			"when": 1631786914476
		},
		{
			"type": "died",
			"when": 1631792492384
		}
	],
	"scrape_ct": 16,
	"next_scrape": 1631879706322,
	"category": "clicker",
	"last_update": 1631752490742,
	"output": [
		{
			"args": {},
			"calls": 1284359,
			"base": "~~ `NCLICKER` `hGENERIC` `JRUSH` `HEX` `IPLUS` `DGAMMA` ~~\n\n`NCLICK` FOR `ICLICKS`\n`NCLICK` FOR `DGLORY`",
			"fragments": [
				"neath",
				"iscard ",
				"d stack",
				"d pile ",
				"B in a ",
				" my fai",
				"y failed",
				"y attack",
				"ttack fa",
				"scard pi",
				"Place my",
				"pile ben",
				"n a disc",
				"my faile",
				"My attac",
				"led stac",
				"k fails.",
				"ils.\\n20",
				"failed s",
				"e beneat",
				"ce my fa",
				"card pil",
				"CA Place",
				"ard pile",
				"ailed st",
				"ack fail",
				"ace my f",
				"a discar",
				"20CB in ",
				"20CA Pla",
				"0CA Plac",
				" Place m",
				" pile be",
				" attack ",
				"stack\\n20",
				"k\\n20CB i",
				"fails.\\n2",
				"ck\\n20CB ",
				"ack\\n20CB",
				"\\n20CA Pl",
				".\\n20CA P"
			],
			"hits": [
				{
					"document": "MFT0XBF_CLST0X7A_SECT0XF227_FILE0X2BC7D171",
					"frags": [
						"beneat",
						"stack\\n",
						" pile b",
						"my faile",
						"led stac",
						" Place m"
					]
				}
			]
		},
		{
			"args": {
				"click": true
			},
			"calls": 1369215,
			"base": "I CANT HEAR YOU! `NCLICK` HARDER",
			"fragments": [
				"neath",
				"iscard ",
				"d stack",
				"d pile ",
				"B in a ",
				" my fai",
				"y failed",
				"y attack",
				"ttack fa",
				"scard pi",
				"Place my",
				"pile ben",
				"n a disc",
				"my faile",
				"My attac",
				"led stac",
				"k fails.",
				"ils.\\n20",
				"failed s",
				"e beneat",
				"ce my fa",
				"card pil",
				"CA Place",
				"ard pile",
				"ailed st",
				"ack fail",
				"ace my f",
				"a discar",
				"20CB in ",
				"20CA Pla",
				"0CA Plac",
				" Place m",
				" pile be",
				" attack ",
				"stack\\n20",
				"k\\n20CB i",
				"fails.\\n2",
				"ck\\n20CB ",
				"ack\\n20CB",
				"\\n20CA Pl",
				".\\n20CA P"
			],
			"hits": [
				{
					"document": "MFT0XBF_CLST0X7A_SECT0XF227_FILE0X2BC7D171",
					"frags": [
						"beneat",
						"stack\\n",
						" pile b",
						"my faile",
						"led stac",
						" Place m"
					]
				}
			]
		},
		{
			"args": {
				"CLICK": true
			},
			"calls": 498140,
			"base": "`LCLICK SECURED`",
			"fragments": [
				"neath",
				"iscard ",
				"d stack",
				"d pile ",
				"B in a ",
				" my fai",
				"y failed",
				"y attack",
				"ttack fa",
				"scard pi",
				"Place my",
				"pile ben",
				"n a disc",
				"my faile",
				"My attac",
				"led stac",
				"k fails.",
				"ils.\\n20",
				"failed s",
				"e beneat",
				"ce my fa",
				"card pil",
				"CA Place",
				"ard pile",
				"ailed st",
				"ack fail",
				"ace my f",
				"a discar",
				"20CB in ",
				"20CA Pla",
				"0CA Plac",
				" Place m",
				" pile be",
				" attack ",
				"stack\\n20",
				"k\\n20CB i",
				"fails.\\n2",
				"ck\\n20CB ",
				"ack\\n20CB",
				"\\n20CA Pl",
				".\\n20CA P"
			],
			"hits": [
				{
					"document": "MFT0XBF_CLST0X7A_SECT0XF227_FILE0X2BC7D171",
					"frags": [
						"beneat",
						"stack\\n",
						" pile b",
						"my faile",
						"led stac",
						" Place m"
					]
				}
			]
		},
		{
			"args": {
				"CLICK": true
			},
			"calls": 1944,
			"base": "`LCLIC  SECURED`",
			"fragments": [
				"K a di",
				"a diCK",
				" a diK",
				"ls.\\n2K",
				"Kls.\\n2",
				"Ked sta",
				"K  a di",
				"ed staK",
				"K S a di",
				"K ls.\\n2",
				"K ed sta",
				"Ky attack",
				"Kack fail",
				"K Sls.\\n2",
				"K Sed sta",
				"\\n20CA Pl"
			]
		},
		{
			"args": {
				"CLICK": true
			},
			"calls": 2913,
			"base": "`LCLICK  ECURED`",
			"fragments": [
				"stackS",
				"Sstack",
				"Sled s",
				"S atta",
				"S a di",
				"led sS",
				" attaS",
				" a diS",
				"tack fS",
				"stack S",
				"Stack f",
				"Sls.\\n2",
				"SEstack",
				"SEled s",
				"Sed sta",
				"SE atta",
				"SE a di",
				"SA Plac",
				"ls.\\n2S",
				"led s S",
				"ed staS",
				"A PlacS",
				" atta S",
				" a di S",
				"tack f S",
				"stackK S",
				"ls.\\n2 S",
				"led sK S",
				"ed sta S",
				"B in a S",
				"ack faiS",
				"A Plac S",
				" attaK S",
				" a diK S",
				"y attackS",
				"tack fK S",
				"ls.\\n2K S",
				"ed staK S",
				"ce my faS",
				"B in a  S",
				"ack\\n20CB",
				"ack failS",
				"ack fai S",
				"A PlacK S",
				"\\n20CA Pl",
				".\\n20CA P"
			]
		}
	],
	"updt": 1631786937952,
	"edit": 338,
	"identified": [
		{
			"document": "MFT0XBF_CLST0X7A_SECT0XF227_FILE0X2BC7D171",
			"frags": [
				"beneat",
				"stack\\n",
				" pile b",
				"my faile",
				"led stac",
				" Place m"
			]
		}
	],
	"pl_output": "{\"ok\":false,\"msg\":\"RUNTIME ERROR abndnd_uy7llh.bot_scam_do_not_run: script doesn't exist\"}"
}