{
	"_id": "abndnd_y2f9qc.leda_4",
	"type": "fragment",
	"mode": "npc",
	"script": "abndnd_y2f9qc.leda_4",
	"sector": "NGC_3281",
	"sec_level": 4,
	"date_added": 1636798883402,
	"last_scraped": 1638164798373,
	"script_log": [
		{
			"type": "added",
			"when": 1636798883402
		}
	],
	"next_scrape": 1638210805724,
	"category": "dice_roller",
	"last_update": 1638164798373,
	"output": [
		{
			"args": {},
			"calls": 1186088,
			"base": "Roll the dice!(tm)\n\nbeat the house's roll to win! {roll:true}",
			"fragments": [
				"XD0_S",
				"R | T",
				"irfee",
				"DY Ai",
				"i extn",
				"0_SECT",
				"X04CF_F",
				"T0X3F_C",
				"IME ERR",
				" NETW E",
				"ROR | US",
				"LE0X7ED7",
				"l-addr |"
			],
			"hits": [
				{
					"document": "MFT0X3F_CLST0XD0_SECT0X04CF_FILE0X7ED7C93F",
					"frags": [
						"R | T",
						"DY Ai",
						"0_SECT",
						"X04CF_F",
						"T0X3F_C",
						"IME ERR",
						"l-addr |"
					]
				}
			]
		}
	],
	"updt": 1638158794591,
	"edit": 239,
	"identified": [
		{
			"document": "MFT0X3F_CLST0XD0_SECT0X04CF_FILE0X7ED7C93F",
			"frags": [
				"R | T",
				"DY Ai",
				"0_SECT",
				"X04CF_F",
				"T0X3F_C",
				"IME ERR",
				"l-addr |"
			]
		}
	]
}