{
	"_id": "anonymous_3840sk.combined_top",
	"type": "fragment",
	"mode": "npc",
	"script": "anonymous_3840sk.combined_top",
	"sector": "K_9541",
	"sec_level": 4,
	"date_added": 1635659070666,
	"last_scraped": 1638059216566,
	"script_log": [
		{
			"type": "added",
			"when": 1635659070666
		}
	],
	"next_scrape": 1638099777604,
	"category": "dice_roller",
	"last_update": 1638059216566,
	"output": [
		{
			"args": {},
			"calls": 1895283,
			"base": "Roll the dice!(tm)\n\nbeat the house's roll to win! {roll:true}",
			"fragments": [
				"s wha",
				"l, it",
				"ld. Th",
				"lable ",
				"h avai",
				"ey bui",
				". They",
				"ild wit",
				"erial, ",
				"y build ",
				"what the",
				"they do.",
				"d with a",
				"build wi",
				" with av",
				" materia"
			],
			"hits": [
				{
					"document": "MFT0XE7_CLST0X7B_SECT0X8CA8_FILE0X5C879769",
					"frags": [
						"ld. Th",
						"lable ",
						"h avai",
						"ey bui",
						"ild wit",
						"erial, ",
						"y build ",
						"they do.",
						"build wi",
						" with av",
						" materia"
					]
				}
			]
		}
	],
	"updt": 1638053476018,
	"edit": 415,
	"identified": [
		{
			"document": "MFT0XE7_CLST0X7B_SECT0X8CA8_FILE0X5C879769",
			"frags": [
				"ld. Th",
				"lable ",
				"h avai",
				"ey bui",
				"ild wit",
				"erial, ",
				"y build ",
				"they do.",
				"build wi",
				" with av",
				" materia"
			]
		}
	]
}