{
	"_id": "derelict_5q1af9.thatguy",
	"type": "fragment",
	"mode": "fresh",
	"script": "derelict_5q1af9.thatguy",
	"sector": "NGC_5122",
	"sec_level": 4,
	"date_added": 1651542571584,
	"last_scraped": 1651542960660,
	"script_log": [
		{
			"type": "added",
			"when": 1651542571584
		}
	],
	"updt": 1651542811114,
	"edit": 2,
	"scrape_ct": 12,
	"next_scrape": 1651543020660,
	"category": "clicker",
	"last_update": 1651542960660,
	"output": [
		{
			"args": {},
			"calls": 11740,
			"base": "~~ `NCLICKER` `hGENERIC` `JRUSH` `HEX` `IPLUS` `DGAMMA` ~~\n\n`NCLICK` FOR `ICLICKS`\n`NCLICK` FOR `DGLORY`",
			"fragments": [
				" 1111 ",
				"111 000",
				"0111 111",
				" 0000 00"
			],
			"hits": [
				{
					"document": "NOT FOUND",
					"frags": [
						" 1111 ",
						"111 000",
						"0111 111",
						" 0000 00"
					]
				}
			]
		},
		{
			"args": {
				"click": true
			},
			"calls": 15058,
			"base": "I CANT HEAR YOU! `NCLICK` HARDER",
			"fragments": [
				" 1111 ",
				"111 000",
				"0111 111",
				" 0000 00"
			]
		},
		{
			"args": {
				"CLICK": true
			},
			"calls": 2276,
			"base": "`LCLICK SECURED`",
			"fragments": [
				" 1111 ",
				"111 000",
				"0111 111",
				" 0000 00"
			]
		},
		{
			"args": {
				"CLICK": true
			},
			"calls": 1130,
			"base": "`LCLICK SE1URED`",
			"fragments": [
				"111 1C",
				" 1111C",
				"111 1EC",
				" 1111EC",
				" 1111 C",
				"111 1SEC",
				"111 000C",
				" 1111SEC",
				" 1111 EC",
				"111 000EC",
				"0111 111C",
				" 0000 00C",
				"111 000SEC",
				"0111 111EC",
				"0000 00SEC",
				" 0000 00EC",
				"0111 111SEC"
			]
		}
	],
	"identified": [
		{
			"document": "NOT FOUND",
			"frags": [
				" 1111 ",
				"111 000",
				"0111 111",
				" 0000 00"
			]
		}
	]
}