{
	"_id": "derelict_6nddzw.ate",
	"type": "fragment",
	"mode": "npc",
	"script": "derelict_6nddzw.ate",
	"sector": "VNP_7578",
	"sec_level": 4,
	"date_added": 1653400970181,
	"last_scraped": 1657081218042,
	"script_log": [
		{
			"type": "added",
			"when": 1653400970181
		}
	],
	"updt": 1657072627517,
	"edit": 411,
	"next_scrape": 1657124998932,
	"category": "clicker",
	"last_update": 1657081199391,
	"output": [
		{
			"args": {},
			"calls": 1386425,
			"base": "~~ `NCLICKER` `hGENERIC` `JRUSH` `HEX` `IPLUS` `DGAMMA` ~~\n\n`NCLICK` FOR `ICLICKS`\n`NCLICK` FOR `DGLORY`",
			"fragments": [
				"ing t",
				"time/e",
				"nvest ",
				"est th",
				"ELY 'E",
				" not h",
				" have ",
				"DTRACK.",
				"r GUIs h",
				"ave AN A"
			],
			"hits": [
				{
					"document": "MFT0XE1_CLST0X61_SECT0X665E_FILE0X0D96F593",
					"frags": [
						"ing t",
						"time/e",
						"GUIs h",
						"est th",
						" not h",
						"DTRACK.",
						"ave AN A"
					]
				}
			]
		},
		{
			"args": {
				"click": true
			},
			"calls": 1465855,
			"base": "I CANT HEAR YOU! `NCLICK` HARDER",
			"fragments": [
				"ing t",
				"time/e",
				"nvest ",
				"est th",
				"ELY 'E",
				" not h",
				" have ",
				"DTRACK.",
				"r GUIs h",
				"ave AN A"
			],
			"hits": [
				{
					"document": "MFT0XE1_CLST0X61_SECT0X665E_FILE0X0D96F593",
					"frags": [
						"ing t",
						"time/e",
						"GUIs h",
						"est th",
						" not h",
						"DTRACK.",
						"ave AN A"
					]
				}
			]
		},
		{
			"args": {
				"CLICK": true
			},
			"calls": 536981,
			"base": "`LCLICK SECURED`",
			"fragments": [
				"ing t",
				"time/e",
				"nvest ",
				"est th",
				"ELY 'E",
				" not h",
				" have ",
				"DTRACK.",
				"r GUIs h",
				"ave AN A"
			],
			"hits": [
				{
					"document": "MFT0XE1_CLST0X61_SECT0X665E_FILE0X0D96F593",
					"frags": [
						"ing t",
						"time/e",
						"GUIs h",
						"est th",
						" not h",
						"DTRACK.",
						"ave AN A"
					]
				}
			]
		}
	],
	"identified": [
		{
			"document": "MFT0XE1_CLST0X61_SECT0X665E_FILE0X0D96F593",
			"frags": [
				"ing t",
				"time/e",
				"GUIs h",
				"est th",
				" not h",
				"DTRACK.",
				"ave AN A"
			]
		}
	]
}