{
	"_id": "derelict_6xzui1.blib",
	"type": "fragment",
	"mode": "dead",
	"script": "derelict_6xzui1.blib",
	"sector": "NGC_2730",
	"sec_level": 4,
	"date_added": 1619216581175,
	"last_scraped": 1619216980115,
	"script_log": [
		{
			"type": "added",
			"when": 1619216581175
		},
		{
			"type": "died",
			"when": 1619488719304
		},
		{
			"type": "died",
			"when": 1622510985114
		},
		{
			"type": "died",
			"when": 1622511007796
		},
		{
			"type": "died",
			"when": 1625436508927
		}
	],
	"updt": 1622550608813,
	"edit": 5,
	"scrape_ct": 13,
	"next_scrape": 1619217040115,
	"category": "clicker",
	"last_update": 1619216980115,
	"output": [
		{
			"args": {},
			"calls": 41250,
			"base": "~~ `NCLICKER` `hGENERIC` `JRUSH` `HEX` `IPLUS` `DGAMMA` ~~\n\n`NCLICK` FOR `ICLICKS`\n`NCLICK` FOR `DGLORY`",
			"fragments": [
				"onsen",
				"n pri",
				"n cri",
				"at ma",
				" deem",
				"ed unp",
				"able o",
				"sus on ",
				"unpreced",
				"sensus o",
				"el issue"
			],
			"hits": [
				{
					"document": "NOT FOUND",
					"frags": [
						"n pri",
						"n cri",
						" deem",
						"ed unp",
						"able o",
						"unpreced",
						"el issue"
					]
				},
				{
					"document": "MFT0XF1_CLST0X75_SECT0X73F7_FILE0X9CB5E952",
					"frags": [
						"onsen",
						"sus on ",
						"sensus o"
					]
				},
				{
					"document": "MFT0XA2_CLST0XE0_SECT0XF623_FILE0XCC32859D",
					"frags": [
						"onsen"
					]
				},
				{
					"document": "MFT0X44_CLST0X35_SECT0XA43B_FILE0XDD1A6B85",
					"frags": [
						"at ma"
					]
				},
				{
					"document": "MFT0XD1_CLST0X95_SECT0X23E7_FILE0X8CAB060B",
					"frags": [
						"at ma"
					]
				},
				{
					"document": "MFT0XBF_CLST0X7A_SECT0XF227_FILE0X2BC7D171",
					"frags": [
						"at ma"
					]
				},
				{
					"document": "MFT0XF4_CLST0XCC_SECT0X7BE4_FILE0XE2A8BDD4",
					"frags": [
						"at ma"
					]
				}
			]
		},
		{
			"args": {
				"click": true
			},
			"calls": 15078,
			"base": "I CANT HEAR YOU! `NCLICK` HARDER",
			"fragments": [
				"onsen",
				"n pri",
				"n cri",
				"at ma",
				" deem",
				"ed unp",
				"able o",
				"sus on ",
				"unpreced",
				"sensus o",
				"el issue"
			],
			"hits": [
				{
					"document": "NOT FOUND",
					"frags": [
						"n pri",
						"n cri",
						" deem",
						"ed unp",
						"able o",
						"unpreced",
						"el issue"
					]
				},
				{
					"document": "MFT0XF1_CLST0X75_SECT0X73F7_FILE0X9CB5E952",
					"frags": [
						"onsen",
						"sus on ",
						"sensus o"
					]
				},
				{
					"document": "MFT0XA2_CLST0XE0_SECT0XF623_FILE0XCC32859D",
					"frags": [
						"onsen"
					]
				},
				{
					"document": "MFT0X44_CLST0X35_SECT0XA43B_FILE0XDD1A6B85",
					"frags": [
						"at ma"
					]
				},
				{
					"document": "MFT0XD1_CLST0X95_SECT0X23E7_FILE0X8CAB060B",
					"frags": [
						"at ma"
					]
				},
				{
					"document": "MFT0XBF_CLST0X7A_SECT0XF227_FILE0X2BC7D171",
					"frags": [
						"at ma"
					]
				},
				{
					"document": "MFT0XF4_CLST0XCC_SECT0X7BE4_FILE0XE2A8BDD4",
					"frags": [
						"at ma"
					]
				}
			]
		},
		{
			"args": {
				"CLICK": true
			},
			"calls": 1920,
			"base": "`LCLICK SECURED`",
			"fragments": [
				"onsen",
				"n pri",
				"n cri",
				"at ma",
				" deem",
				"ed unp",
				"able o",
				"sus on ",
				"unpreced",
				"sensus o",
				"el issue"
			],
			"hits": [
				{
					"document": "NOT FOUND",
					"frags": [
						"n pri",
						"n cri",
						" deem",
						"ed unp",
						"able o",
						"unpreced",
						"el issue"
					]
				},
				{
					"document": "MFT0XF1_CLST0X75_SECT0X73F7_FILE0X9CB5E952",
					"frags": [
						"onsen",
						"sus on ",
						"sensus o"
					]
				},
				{
					"document": "MFT0XA2_CLST0XE0_SECT0XF623_FILE0XCC32859D",
					"frags": [
						"onsen"
					]
				},
				{
					"document": "MFT0X44_CLST0X35_SECT0XA43B_FILE0XDD1A6B85",
					"frags": [
						"at ma"
					]
				},
				{
					"document": "MFT0XD1_CLST0X95_SECT0X23E7_FILE0X8CAB060B",
					"frags": [
						"at ma"
					]
				},
				{
					"document": "MFT0XBF_CLST0X7A_SECT0XF227_FILE0X2BC7D171",
					"frags": [
						"at ma"
					]
				},
				{
					"document": "MFT0XF4_CLST0XCC_SECT0X7BE4_FILE0XE2A8BDD4",
					"frags": [
						"at ma"
					]
				}
			]
		}
	],
	"identified": [
		{
			"document": "NOT FOUND",
			"frags": [
				"n pri",
				"n cri",
				" deem",
				"ed unp",
				"able o",
				"unpreced",
				"el issue"
			]
		},
		{
			"document": "MFT0XF1_CLST0X75_SECT0X73F7_FILE0X9CB5E952",
			"frags": [
				"onsen",
				"sus on ",
				"sensus o"
			]
		},
		{
			"document": "MFT0XA2_CLST0XE0_SECT0XF623_FILE0XCC32859D",
			"frags": [
				"onsen"
			]
		},
		{
			"document": "MFT0X44_CLST0X35_SECT0XA43B_FILE0XDD1A6B85",
			"frags": [
				"at ma"
			]
		},
		{
			"document": "MFT0XD1_CLST0X95_SECT0X23E7_FILE0X8CAB060B",
			"frags": [
				"at ma"
			]
		},
		{
			"document": "MFT0XBF_CLST0X7A_SECT0XF227_FILE0X2BC7D171",
			"frags": [
				"at ma"
			]
		},
		{
			"document": "MFT0XF4_CLST0XCC_SECT0X7BE4_FILE0XE2A8BDD4",
			"frags": [
				"at ma"
			]
		}
	],
	"retry_args": [
		{
			"click": true
		},
		{
			"CLICK": true
		}
	]
}