{
	"_id": "derelict_vm3kvh.synapse",
	"type": "fragment",
	"mode": "dead",
	"script": "derelict_vm3kvh.synapse",
	"sector": "HJG_9563",
	"sec_level": 2,
	"date_added": 1623499571821,
	"last_scraped": 0,
	"script_log": [
		{
			"type": "added",
			"when": 1623499571821
		},
		{
			"type": "died",
			"when": 1626168335032
		},
		{
			"type": "died",
			"when": 1627098914976
		},
		{
			"type": "died",
			"when": 1629239163664
		},
		{
			"type": "died",
			"when": 1629239172401
		},
		{
			"type": "died",
			"when": 1629239189589
		},
		{
			"type": "died",
			"when": 1629239233827
		},
		{
			"type": "died",
			"when": 1629239243798
		},
		{
			"type": "died",
			"when": 1629255737889
		},
		{
			"type": "died",
			"when": 1629255751398
		},
		{
			"type": "died",
			"when": 1629255762814
		},
		{
			"type": "died",
			"when": 1629255824248
		},
		{
			"type": "died",
			"when": 1629255833911
		}
	],
	"updt": 1627139857432,
	"edit": 4
}