{
	"_id": "uknown_l63rse.nfo",
	"type": "fragment",
	"mode": "dead",
	"script": "uknown_l63rse.nfo",
	"sector": "VNP_5798",
	"sec_level": 4,
	"date_added": 1608080803031,
	"last_scraped": 1619336677120,
	"script_log": [
		{
			"type": "added",
			"when": 1608080803031
		},
		[
			{
				"type": "sector change",
				"when": 1613748409698,
				"from": "VNP_5798",
				"to": "HJG_3792"
			}
		],
		{
			"type": "died",
			"when": 1619865728480
		},
		{
			"type": "died",
			"when": 1622510985114
		},
		{
			"type": "died",
			"when": 1622511007796
		},
		{
			"type": "died",
			"when": 1625436508927
		},
		{
			"type": "died",
			"when": 1627098914976
		},
		{
			"type": "died",
			"when": 1629239163664
		},
		{
			"type": "died",
			"when": 1629239172401
		},
		{
			"type": "died",
			"when": 1629239189589
		},
		{
			"type": "died",
			"when": 1629239233827
		},
		{
			"type": "died",
			"when": 1629239243798
		},
		{
			"type": "died",
			"when": 1629255737889
		},
		{
			"type": "died",
			"when": 1629255751398
		},
		{
			"type": "died",
			"when": 1629255762814
		},
		{
			"type": "died",
			"when": 1629255824248
		},
		{
			"type": "died",
			"when": 1629255833911
		}
	],
	"pl_output": "{\"version\":\"1.0.0\",\"scripts\":{\"math\":{\"usage\":\"{ e: \\\"expression\\\", env: {x: 4} }\",\"desc\":\"Fairly simple math expression parser, check dtr.man{page:\\\"dapper.math\\\"} for more info\",\"args\":[{\"name\":\"e\",\"type\":\"string\",\"optional\":false,\"desc\":\"expression to be parsed\"},{\"name\":\"env\",\"type\":\"object\",\"optional\":true,\"desc\":\"key:value pairs of external variables to inject\"}],\"returns\":\"ok object if called from scriptor, otherwise string\",\"subscript\":true,\"scriptor\":true,\"cli\":true}}}",
	"next_scrape": 1619419877867,
	"updt": 1627133017864,
	"edit": 4997
}