{
	"_id": "unidentified_zr9rr1.data",
	"type": "fragment",
	"mode": "npc",
	"script": "unidentified_zr9rr1.data",
	"sector": "NGC_1466",
	"sec_level": 4,
	"date_added": 1651636419702,
	"last_scraped": 1651644241204,
	"script_log": [
		{
			"type": "added",
			"when": 1651636419702
		}
	],
	"next_scrape": 1651685250140,
	"category": "clicker",
	"last_update": 1651644241204,
	"output": [
		{
			"args": {},
			"calls": 41534,
			"base": "~~ `NCLICKER` `hGENERIC` `JRUSH` `HEX` `IPLUS` `DGAMMA` ~~\n\n`NCLICK` FOR `ICLICKS`\n`NCLICK` FOR `DGLORY`",
			"fragments": [
				"y in E",
				"R SPEC",
				"ntion ",
				"ole to ",
				"ers to ",
				" EXPECT"
			],
			"hits": [
				{
					"document": "MFT0XE1_CLST0X61_SECT0X665E_FILE0X0D96F593",
					"frags": [
						"y in E",
						"R SPEC",
						"ntion ",
						"ole to ",
						"ers to ",
						" EXPECT"
					]
				}
			]
		},
		{
			"args": {
				"click": true
			},
			"calls": 35770,
			"base": "I CANT HEAR YOU! `NCLICK` HARDER",
			"fragments": [
				"y in E",
				"R SPEC",
				"ntion ",
				"ole to ",
				"ers to ",
				" EXPECT"
			]
		},
		{
			"args": {
				"CLICK": true
			},
			"calls": 14607,
			"base": "`LCLICK SECURED`",
			"fragments": [
				"y in E",
				"R SPEC",
				"ntion ",
				"ole to ",
				"ers to ",
				" EXPECT"
			]
		}
	],
	"identified": [
		{
			"document": "MFT0XE1_CLST0X61_SECT0X665E_FILE0X0D96F593",
			"frags": [
				"y in E",
				"R SPEC",
				"ntion ",
				"ole to ",
				"ers to ",
				" EXPECT"
			]
		}
	],
	"updt": 1651637586622,
	"edit": 5
}