{
	"_id": "unidentified_jw7nm1.man",
	"type": "fragment",
	"mode": "dead",
	"script": "unidentified_jw7nm1.man",
	"sector": "K_5413",
	"sec_level": 4,
	"date_added": 1597241879095,
	"last_scraped": 1597241968730,
	"script_log": [
		{
			"type": "added",
			"when": 1597241879095
		},
		{
			"type": "died",
			"when": 1599819269986
		},
		{
			"type": "died",
			"when": 1603129869622
		},
		{
			"type": "died",
			"when": 1603284151302
		},
		{
			"type": "died",
			"when": 1603434543750
		},
		{
			"type": "died",
			"when": 1603434642646
		},
		{
			"type": "died",
			"when": 1603597711089
		},
		{
			"type": "died",
			"when": 1603774474467
		},
		{
			"type": "died",
			"when": 1603939894684
		},
		{
			"type": "died",
			"when": 1604017212499
		},
		{
			"type": "died",
			"when": 1604172613247
		},
		{
			"type": "died",
			"when": 1604172623611
		},
		{
			"type": "died",
			"when": 1607134720682
		},
		{
			"type": "died",
			"when": 1607276475243
		},
		{
			"type": "died",
			"when": 1607447436906
		},
		{
			"type": "died",
			"when": 1607447532637
		},
		{
			"type": "died",
			"when": 1607448415208
		},
		{
			"type": "died",
			"when": 1608925453008
		},
		{
			"type": "died",
			"when": 1609165709899
		},
		{
			"type": "died",
			"when": 1609387844235
		},
		{
			"type": "died",
			"when": 1609639526034
		},
		{
			"type": "died",
			"when": 1609908294705
		},
		{
			"type": "died",
			"when": 1617291633650
		},
		{
			"type": "died",
			"when": 1622510985114
		},
		{
			"type": "died",
			"when": 1622511007796
		},
		{
			"type": "died",
			"when": 1625436508927
		},
		{
			"type": "died",
			"when": 1627098914976
		},
		{
			"type": "died",
			"when": 1629239163664
		},
		{
			"type": "died",
			"when": 1629239172401
		},
		{
			"type": "died",
			"when": 1629239189589
		},
		{
			"type": "died",
			"when": 1629239233827
		},
		{
			"type": "died",
			"when": 1629239243798
		},
		{
			"type": "died",
			"when": 1629255737889
		},
		{
			"type": "died",
			"when": 1629255751398
		},
		{
			"type": "died",
			"when": 1629255762814
		},
		{
			"type": "died",
			"when": 1629255824248
		},
		{
			"type": "died",
			"when": 1629255833911
		}
	],
	"scrape_ct": 16,
	"next_scrape": 1597242028730,
	"category": "UNKNOWN CATEGORY",
	"last_update": 1597241968730,
	"output": [
		{
			"args": {},
			"calls": 9336,
			"base": "YOU COULD WIN 61GC with do:\"win\"\n\nOR\n\nYOU COULD `VLOSE`",
			"fragments": [
				"No ET",
				"of ope",
				"Hyperi",
				"0\\n{\"d",
				"turn\\\" ",
				"tor ser",
				"news\",\"",
				"or retur"
			],
			"hits": [
				{
					"document": "MFT0X87_CLST0X1C_SECT0XA42E_FILE0XE19B2A90",
					"frags": [
						"No ET",
						"of ope",
						"Hyperi",
						"0\\n{\"d",
						"turn\\\" ",
						"tor ser",
						"news\",\"",
						"or retur"
					]
				}
			]
		}
	],
	"updt": 1629286656513,
	"edit": 24,
	"identified": [
		{
			"document": "MFT0X87_CLST0X1C_SECT0XA42E_FILE0XE19B2A90",
			"frags": [
				"No ET",
				"of ope",
				"Hyperi",
				"0\\n{\"d",
				"turn\\\" ",
				"tor ser",
				"news\",\"",
				"or retur"
			]
		}
	]
}