{
	"_id": "unidentified_8q2di8.bot_scam_do_not_run",
	"type": "fragment",
	"mode": "npc",
	"script": "unidentified_8q2di8.bot_scam_do_not_run",
	"sector": "HJG_7083",
	"sec_level": 4,
	"date_added": 1631983536181,
	"last_scraped": 1632796483780,
	"script_log": [
		{
			"type": "added",
			"when": 1631983536181
		}
	],
	"updt": 1632787582992,
	"edit": 107,
	"next_scrape": 1632839861221,
	"category": "plant_sim",
	"last_update": 1632796483780,
	"output": [
		{
			"args": {},
			"calls": 4535,
			"base": "c:\"pjjsoq\" d:\"<f l n s w>\"\n\n\n\n\n\n                 \n                 .\n                 ",
			"fragments": [
				"jk ##",
				" ## N",
				"afford",
				" front",
				" ## Al",
				"right. ",
				"t up as ",
				"ront of ",
				"as we go"
			],
			"hits": [
				{
					"document": "MFT0X71_CLST0X8A_SECT0X7356_FILE0X14AFF93F",
					"frags": [
						"jk ##",
						" ## N",
						"afford",
						" front",
						" ## Al",
						"right. ",
						"t up as ",
						"ront of ",
						"as we go"
					]
				}
			]
		},
		{
			"args": {},
			"calls": 19102,
			"base": "c:\"pjjsoq\" d:\"<f l n s w>\"\n\n\n\n\n\n                 \n                 Ã\n                 ",
			"fragments": [
				"jk ##",
				" ## N",
				"afford",
				" front",
				" ## Al",
				"right. ",
				"t up as ",
				"ront of ",
				"as we go"
			]
		},
		{
			"args": {},
			"calls": 75677,
			"base": "c:\"pjjsoq\" d:\"<f l n s w>\"\n\n\n\n\n\n\n\n          ~~~~~~~~~~~~~~",
			"fragments": [
				"k ## ",
				"acks ",
				" trac",
				" to b",
				" ## N",
				"t of u",
				"p as w",
				"No, Io",
				"ng the",
				"Iona! ",
				"in fro",
				"g the ",
				"afford",
				"! ## j",
				" No, I",
				" ## Al",
				"right. ",
				"n't aff",
				"e can't",
				"cks in ",
				"## Alri",
				"t up as ",
				"ront of ",
				"f us. I ",
				"e it up ",
				"as we go",
				"## jk ##",
				" of us. ",
				" front o",
				" Alright",
				" ## jk #"
			]
		}
	],
	"identified": [
		{
			"document": "MFT0X71_CLST0X8A_SECT0X7356_FILE0X14AFF93F",
			"frags": [
				"jk ##",
				" ## N",
				"afford",
				" front",
				" ## Al",
				"right. ",
				"t up as ",
				"ront of ",
				"as we go"
			]
		}
	]
}