{
	"_id": "unidentified_7dlljz.com",
	"type": "fragment",
	"mode": "dead",
	"script": "unidentified_7dlljz.com",
	"sector": "HJG_1950",
	"sec_level": 4,
	"date_added": 1628532334833,
	"last_scraped": 1630365401916,
	"script_log": [
		{
			"type": "added",
			"when": 1628532334833
		},
		{
			"type": "died",
			"when": 1631983536307
		}
	],
	"scrape_ct": 16,
	"next_scrape": 1630408059981,
	"category": "clicker",
	"last_update": 1630365401916,
	"output": [
		{
			"args": {},
			"calls": 495381,
			"base": "~~ `NCLICKER` `hGENERIC` `JRUSH` `HEX` `IPLUS` `DGAMMA` ~~\n\n`NCLICK` FOR `ICLICKS`\n`NCLICK` FOR `DGLORY`",
			"fragments": [
				"ST ER",
				"G ERR",
				"| USE",
				"| NET",
				"F593\\n",
				"OR | US",
				"ME ERRO",
				"0XE1_CL",
				" TIME E",
				"llister ",
				"0D96F593",
				" PROG ER",
				" ERROR |"
			],
			"hits": [
				{
					"document": "MFT0XE1_CLST0X61_SECT0X665E_FILE0X0D96F593",
					"frags": [
						"ST ER",
						"G ERR",
						"| USE",
						"| NET",
						"F593\\n",
						"OR | US",
						"ME ERRO",
						"0XE1_CL",
						" TIME E",
						"llister ",
						"0D96F593",
						" PROG ER",
						" ERROR |"
					]
				}
			]
		},
		{
			"args": {
				"click": true
			},
			"calls": 496802,
			"base": "I CANT HEAR YOU! `NCLICK` HARDER",
			"fragments": [
				"ST ER",
				"G ERR",
				"| USE",
				"| NET",
				"F593\\n",
				"OR | US",
				"ME ERRO",
				"0XE1_CL",
				" TIME E",
				"llister ",
				"0D96F593",
				" PROG ER",
				" ERROR |"
			],
			"hits": [
				{
					"document": "MFT0XE1_CLST0X61_SECT0X665E_FILE0X0D96F593",
					"frags": [
						"ST ER",
						"G ERR",
						"| USE",
						"| NET",
						"F593\\n",
						"OR | US",
						"ME ERRO",
						"0XE1_CL",
						" TIME E",
						"llister ",
						"0D96F593",
						" PROG ER",
						" ERROR |"
					]
				}
			]
		},
		{
			"args": {
				"CLICK": true
			},
			"calls": 176271,
			"base": "`LCLICK SECURED`",
			"fragments": [
				"ST ER",
				"G ERR",
				"| USE",
				"| NET",
				"F593\\n",
				"OR | US",
				"ME ERRO",
				"0XE1_CL",
				" TIME E",
				"llister ",
				"0D96F593",
				" PROG ER",
				" ERROR |"
			],
			"hits": [
				{
					"document": "MFT0XE1_CLST0X61_SECT0X665E_FILE0X0D96F593",
					"frags": [
						"ST ER",
						"G ERR",
						"| USE",
						"| NET",
						"F593\\n",
						"OR | US",
						"ME ERRO",
						"0XE1_CL",
						" TIME E",
						"llister ",
						"0D96F593",
						" PROG ER",
						" ERROR |"
					]
				}
			]
		},
		{
			"args": {
				"CLICK": true
			},
			"calls": 7908,
			"base": "`LCLICK RECURED`",
			"fragments": [
				"SOR | ",
				"SERROR",
				"OR | S",
				"ERRORS",
				"SEOR | ",
				"SEERROR",
				"OR |  S",
				"ERROR S",
				"PROG ERS",
				"OR | USS",
				"OR | K S",
				"ERRORK S",
				"ERROR |S",
				"0XE1_CLS",
				" PROG ER",
				" ERROR |",
				"OR | US S",
				"D96F593 S",
				"0XE1_CL S",
				"0D96F593S"
			],
			"hits": [
				{
					"document": "NOT FOUND",
					"frags": [
						"SOR | ",
						"SERROR",
						"OR | S",
						"ERRORS",
						"SEOR | ",
						"SEERROR",
						"OR |  S",
						"ERROR S",
						"PROG ERS",
						"OR | USS",
						"OR | K S",
						"ERRORK S",
						"ERROR |S",
						"OR | US S",
						"D96F593 S",
						"0XE1_CL S",
						"0D96F593S"
					]
				},
				{
					"document": "MFT0XE1_CLST0X61_SECT0X665E_FILE0X0D96F593",
					"frags": [
						"0XE1_CLS",
						" PROG ER",
						" ERROR |"
					]
				},
				{
					"document": "MFT0X44_CLST0X35_SECT0XA43B_FILE0XDD1A6B85",
					"frags": [
						" PROG ER",
						" ERROR |"
					]
				},
				{
					"document": "MFT0X93_CLST0X0B_SECT0XB1F1_FILE0X17858BD3",
					"frags": [
						" PROG ER",
						" ERROR |"
					]
				},
				{
					"document": "MFT0X3F_CLST0X0A_SECT0X8F99_FILE0XBD88122E",
					"frags": [
						" PROG ER",
						" ERROR |"
					]
				},
				{
					"document": "MFT0X82_CLST0X69_SECT0X885F_FILE0X8C8517B2",
					"frags": [
						" PROG ER",
						" ERROR |"
					]
				},
				{
					"document": "MFT0XCE_CLST0X15_SECT0XAD0C_FILE0X77AB550B",
					"frags": [
						" PROG ER",
						" ERROR |"
					]
				},
				{
					"document": "MFT0XE7_CLST0X7B_SECT0X8CA8_FILE0X5C879769",
					"frags": [
						" PROG ER",
						" ERROR |"
					]
				},
				{
					"document": "MFT0X00_CLST0XF3_SECT0X756A_FILE0XBBE270FC",
					"frags": [
						" PROG ER",
						" ERROR |"
					]
				},
				{
					"document": "MFT0X71_CLST0X8A_SECT0X7356_FILE0X14AFF93F",
					"frags": [
						" PROG ER",
						" ERROR |"
					]
				},
				{
					"document": "MFT0XD1_CLST0X95_SECT0X23E7_FILE0X8CAB060B",
					"frags": [
						" PROG ER",
						" ERROR |"
					]
				},
				{
					"document": "MFT0X3F_CLST0XD0_SECT0X04CF_FILE0X7ED7C93F",
					"frags": [
						" PROG ER",
						" ERROR |"
					]
				},
				{
					"document": "MFT0XF1_CLST0X75_SECT0X73F7_FILE0X9CB5E952",
					"frags": [
						" PROG ER",
						" ERROR |"
					]
				},
				{
					"document": "MFT0XF4_CLST0XCC_SECT0X7BE4_FILE0XE2A8BDD4",
					"frags": [
						" PROG ER",
						" ERROR |"
					]
				},
				{
					"document": "MFT0XA7_CLST0X1F_SECT0X57C3_FILE0X8C911BB8",
					"frags": [
						" PROG ER",
						" ERROR |"
					]
				},
				{
					"document": "MFT0XA2_CLST0XE0_SECT0XF623_FILE0XCC32859D",
					"frags": [
						" PROG ER",
						" ERROR |"
					]
				},
				{
					"document": "MFT0XD7_CLST0XF7_SECT0X1D2F_FILE0X3A848D07",
					"frags": [
						" PROG ER",
						" ERROR |"
					]
				},
				{
					"document": "MFT0XCF_CLST0X84_SECT0X6B58_FILE0X7A81819D",
					"frags": [
						" PROG ER",
						" ERROR |"
					]
				},
				{
					"document": "MFT0X68_CLST0XCA_SECT0X0F5F_FILE0X87AF16DE",
					"frags": [
						" PROG ER",
						" ERROR |"
					]
				},
				{
					"document": "Prisoners",
					"frags": [
						" PROG ER",
						" ERROR |"
					]
				},
				{
					"document": "MFT0X3F_CLST0XE4_SECT0X4FC8_FILE0X08E5E16F",
					"frags": [
						" PROG ER",
						" ERROR |"
					]
				},
				{
					"document": "MFT0XC3_CLST0XC4_SECT0X085A_FILE0X64C10251",
					"frags": [
						" PROG ER",
						" ERROR |"
					]
				},
				{
					"document": "MFT0XFD_CLST0X92_SECT0X2FC4_FILE0X70959CE3",
					"frags": [
						" PROG ER",
						" ERROR |"
					]
				}
			]
		},
		{
			"args": {
				"CLICK": true
			},
			"calls": 3714,
			"base": "`LCLICR SECURED`",
			"fragments": [
				"OR | K",
				"KERROR",
				"ERRORK",
				"OR | CK",
				"ERRORCK",
				"KOR | US",
				"KD96F593",
				"K0XE1_CL",
				"K SOR | ",
				"K0D96F593",
				"K PROG ER",
				"K OR | US",
				"K ERROR |",
				"K D96F593",
				"K 0XE1_CL"
			],
			"hits": [
				{
					"document": "NOT FOUND",
					"frags": [
						"OR | K",
						"KERROR",
						"ERRORK",
						"OR | CK",
						"ERRORCK",
						"KOR | US",
						"KD96F593",
						"K0XE1_CL",
						"K SOR | ",
						"K0D96F593",
						"K PROG ER",
						"K OR | US",
						"K ERROR |",
						"K D96F593",
						"K 0XE1_CL"
					]
				}
			]
		}
	],
	"updt": 1631984352217,
	"edit": 112,
	"identified": [
		{
			"document": "NOT FOUND",
			"frags": [
				"SERROR",
				"OR | S",
				"KERROR",
				"ERRORS",
				"SEOR | ",
				"SEERROR",
				"OR | CK",
				"OR |  S",
				"ERRORCK",
				"ERROR S",
				"PROG ERS",
				"OR | USS",
				"OR | K S",
				"KOR | US",
				"KD96F593",
				"K0XE1_CL",
				"K SOR | ",
				"ERRORK S",
				"ERROR |S",
				"OR | US S",
				"K0D96F593",
				"K PROG ER",
				"K OR | US",
				"K ERROR |",
				"K D96F593",
				"K 0XE1_CL",
				"D96F593 S",
				"0XE1_CL S",
				"0D96F593S"
			]
		},
		{
			"document": "MFT0XE1_CLST0X61_SECT0X665E_FILE0X0D96F593",
			"frags": [
				"ST ER",
				"G ERR",
				"| USE",
				"| NET",
				"F593\\n",
				"OR | US",
				"ME ERRO",
				" TIME E",
				"llister ",
				"0XE1_CLS",
				"0D96F593",
				" PROG ER",
				" ERROR |"
			]
		},
		{
			"document": "MFT0X44_CLST0X35_SECT0XA43B_FILE0XDD1A6B85",
			"frags": [
				" PROG ER",
				" ERROR |"
			]
		},
		{
			"document": "MFT0X93_CLST0X0B_SECT0XB1F1_FILE0X17858BD3",
			"frags": [
				" PROG ER",
				" ERROR |"
			]
		},
		{
			"document": "MFT0X3F_CLST0X0A_SECT0X8F99_FILE0XBD88122E",
			"frags": [
				" PROG ER",
				" ERROR |"
			]
		},
		{
			"document": "MFT0X82_CLST0X69_SECT0X885F_FILE0X8C8517B2",
			"frags": [
				" PROG ER",
				" ERROR |"
			]
		},
		{
			"document": "MFT0XCE_CLST0X15_SECT0XAD0C_FILE0X77AB550B",
			"frags": [
				" PROG ER",
				" ERROR |"
			]
		},
		{
			"document": "MFT0XE7_CLST0X7B_SECT0X8CA8_FILE0X5C879769",
			"frags": [
				" PROG ER",
				" ERROR |"
			]
		},
		{
			"document": "MFT0X00_CLST0XF3_SECT0X756A_FILE0XBBE270FC",
			"frags": [
				" PROG ER",
				" ERROR |"
			]
		},
		{
			"document": "MFT0X71_CLST0X8A_SECT0X7356_FILE0X14AFF93F",
			"frags": [
				" PROG ER",
				" ERROR |"
			]
		},
		{
			"document": "MFT0XD1_CLST0X95_SECT0X23E7_FILE0X8CAB060B",
			"frags": [
				" PROG ER",
				" ERROR |"
			]
		},
		{
			"document": "MFT0X3F_CLST0XD0_SECT0X04CF_FILE0X7ED7C93F",
			"frags": [
				" PROG ER",
				" ERROR |"
			]
		},
		{
			"document": "MFT0XF1_CLST0X75_SECT0X73F7_FILE0X9CB5E952",
			"frags": [
				" PROG ER",
				" ERROR |"
			]
		},
		{
			"document": "MFT0XF4_CLST0XCC_SECT0X7BE4_FILE0XE2A8BDD4",
			"frags": [
				" PROG ER",
				" ERROR |"
			]
		},
		{
			"document": "MFT0XA7_CLST0X1F_SECT0X57C3_FILE0X8C911BB8",
			"frags": [
				" PROG ER",
				" ERROR |"
			]
		},
		{
			"document": "MFT0XA2_CLST0XE0_SECT0XF623_FILE0XCC32859D",
			"frags": [
				" PROG ER",
				" ERROR |"
			]
		},
		{
			"document": "MFT0XD7_CLST0XF7_SECT0X1D2F_FILE0X3A848D07",
			"frags": [
				" PROG ER",
				" ERROR |"
			]
		},
		{
			"document": "MFT0XCF_CLST0X84_SECT0X6B58_FILE0X7A81819D",
			"frags": [
				" PROG ER",
				" ERROR |"
			]
		},
		{
			"document": "MFT0X68_CLST0XCA_SECT0X0F5F_FILE0X87AF16DE",
			"frags": [
				" PROG ER",
				" ERROR |"
			]
		},
		{
			"document": "Prisoners",
			"frags": [
				" PROG ER",
				" ERROR |"
			]
		},
		{
			"document": "MFT0X3F_CLST0XE4_SECT0X4FC8_FILE0X08E5E16F",
			"frags": [
				" PROG ER",
				" ERROR |"
			]
		},
		{
			"document": "MFT0XC3_CLST0XC4_SECT0X085A_FILE0X64C10251",
			"frags": [
				" PROG ER",
				" ERROR |"
			]
		},
		{
			"document": "MFT0XFD_CLST0X92_SECT0X2FC4_FILE0X70959CE3",
			"frags": [
				" PROG ER",
				" ERROR |"
			]
		}
	]
}