{
	"_id": "unidentified_bae3cm.blib",
	"type": "fragment",
	"mode": "skip",
	"script": "unidentified_bae3cm.blib",
	"sector": "K_0473",
	"sec_level": 4,
	"date_added": 1624909995790,
	"last_scraped": 1625460909922,
	"script_log": [
		{
			"type": "added",
			"when": 1624909995790
		}
	],
	"updt": 1624910199399,
	"edit": 2,
	"scrape_ct": 16,
	"next_scrape": 1625507438697,
	"category": "clicker",
	"last_update": 1625460909922,
	"output": [
		{
			"args": {},
			"calls": 13911,
			"base": "~~ `NCLICKER` `hGENERIC` `JRUSH` `HEX` `IPLUS` `DGAMMA` ~~\n\n`NCLICK` FOR `ICLICKS`\n`NCLICK` FOR `DGLORY`",
			"fragments": [
				"nt-in-",
				" what ",
				"what ar",
				"oom tim",
				"y ## It'",
				"he-room ",
				"'s eleph"
			],
			"hits": [
				{
					"document": "MFT0X93_CLST0X0B_SECT0XB1F1_FILE0X17858BD3",
					"frags": [
						"nt-in-",
						" what ",
						"what ar",
						"oom tim",
						"y ## It'",
						"he-room ",
						"'s eleph"
					]
				}
			]
		},
		{
			"args": {
				"click": true
			},
			"calls": 5987,
			"base": "I CANT HEAR YOU! `NCLICK` HARDER",
			"fragments": [
				"nt-in-",
				" what ",
				"what ar",
				"oom tim",
				"y ## It'",
				"he-room ",
				"'s eleph"
			]
		},
		{
			"args": {
				"CLICK": true
			},
			"calls": 6682,
			"base": "`LCLICK SECURED`",
			"fragments": [
				"nt-in-",
				" what ",
				"what ar",
				"oom tim",
				"y ## It'",
				"he-room ",
				"'s eleph"
			]
		}
	],
	"identified": [
		{
			"document": "MFT0X93_CLST0X0B_SECT0XB1F1_FILE0X17858BD3",
			"frags": [
				"nt-in-",
				" what ",
				"what ar",
				"oom tim",
				"y ## It'",
				"he-room ",
				"'s eleph"
			]
		}
	]
}