{
	"_id": "unknown_ug3iql.exapunks",
	"type": "fragment",
	"mode": "dead",
	"script": "unknown_ug3iql.exapunks",
	"sector": "K_2236",
	"sec_level": 4,
	"date_added": 1575091796034,
	"last_scraped": 1575092578611,
	"script_log": [
		{
			"type": "added",
			"when": 1575091796034
		},
		{
			"type": "died",
			"when": 1575363941271
		},
		{
			"type": "died",
			"when": 1576356668404
		},
		{
			"type": "died",
			"when": 1584515942412
		},
		{
			"type": "died",
			"when": 1603129869622
		},
		{
			"type": "died",
			"when": 1603284151302
		},
		{
			"type": "died",
			"when": 1603434543750
		},
		{
			"type": "died",
			"when": 1603434642646
		},
		{
			"type": "died",
			"when": 1603597711089
		},
		{
			"type": "died",
			"when": 1603774474467
		},
		{
			"type": "died",
			"when": 1603939894684
		},
		{
			"type": "died",
			"when": 1604017212499
		},
		{
			"type": "died",
			"when": 1604172612378
		},
		{
			"type": "died",
			"when": 1604172623611
		},
		{
			"type": "died",
			"when": 1607134720682
		},
		{
			"type": "died",
			"when": 1607276475243
		},
		{
			"type": "died",
			"when": 1607447436906
		},
		{
			"type": "died",
			"when": 1607447532637
		},
		{
			"type": "died",
			"when": 1607448415208
		},
		{
			"type": "died",
			"when": 1608925453008
		},
		{
			"type": "died",
			"when": 1609165709899
		},
		{
			"type": "died",
			"when": 1609387844235
		},
		{
			"type": "died",
			"when": 1609639526034
		},
		{
			"type": "died",
			"when": 1609908294705
		},
		{
			"type": "died",
			"when": 1617291633650
		},
		{
			"type": "died",
			"when": 1622510985114
		},
		{
			"type": "died",
			"when": 1622511007796
		},
		{
			"type": "died",
			"when": 1625436508927
		}
	],
	"updt": 1622524412960,
	"edit": 25,
	"retry_args": [
		{
			"do": "win"
		},
		{
			"do": "LOSE"
		}
	],
	"scrape_ct": 16,
	"next_scrape": 1575092638611,
	"category": "risk_factor",
	"last_update": 1575092578611,
	"output": [
		{
			"args": {},
			"calls": 6915,
			"base": "YOU COULD WIN 2GC with do:\"win\"\n\nOR\n\nYOU COULD `VLOSE`",
			"fragments": [
				"ne, t",
				"ig on",
				"e, th",
				"big o",
				"# Hi!",
				"the bi",
				"leem. ",
				"This i",
				". ## H",
				" in Sa",
				"ping in",
				"is is th",
				" is the "
			],
			"hits": [
				{
					"document": "MFT0X93_CLST0X0B_SECT0XB1F1_FILE0X17858BD3",
					"frags": [
						"ne, t",
						"ig on",
						"e, th",
						"big o",
						"# Hi!",
						"the bi",
						"leem. ",
						"This i",
						". ## H",
						" in Sa",
						"ping in",
						"is is th",
						" is the "
					]
				}
			]
		}
	],
	"cannot_identify": true
}