{
	"_id": "unknown_5q3nsk.solvent",
	"type": "fragment",
	"mode": "dead",
	"script": "unknown_5q3nsk.solvent",
	"sector": "VNP_8184",
	"sec_level": 4,
	"date_added": 1672342808697,
	"last_scraped": 1672648901367,
	"script_log": [
		{
			"type": "added",
			"when": 1672342808697
		},
		{
			"type": "died",
			"when": 1672649633217
		}
	],
	"next_scrape": 1672692188386,
	"category": "clicker",
	"last_update": 1672648901367,
	"output": [
		{
			"args": {},
			"calls": 80127,
			"base": "~~ `NCLICKER` `hGENERIC` `JRUSH` `HEX` `IPLUS` `DGAMMA` ~~\n\n`NCLICK` FOR `ICLICKS`\n`NCLICK` FOR `DGLORY`",
			"fragments": [
				"stina",
				"revar",
				"o hav",
				"te and",
				"on't. ",
				"ntimen",
				"t in fi",
				"ricate ",
				"ne this",
				"l. They",
				"ghts an",
				"crastin",
				"and get",
				"varicate",
				"urselves",
				"They don",
				"ntal. Th",
				"imental.",
				"ey don't",
				"e this o"
			],
			"hits": [
				{
					"document": "MFT0X42_CLST0XE9_SECT0X63A2_FILE0X2194137C",
					"frags": [
						"rselv",
						"revar",
						"this o",
						"on't. ",
						"ne thi",
						"nd get",
						"t in fi",
						"crastin",
						"varicate",
						"ntal. Th",
						"imental."
					]
				}
			]
		},
		{
			"args": {
				"click": true
			},
			"calls": 84838,
			"base": "I CANT HEAR YOU! `NCLICK` HARDER",
			"fragments": [
				"stina",
				"revar",
				"o hav",
				"te and",
				"on't. ",
				"ntimen",
				"t in fi",
				"ricate ",
				"ne this",
				"l. They",
				"ghts an",
				"crastin",
				"and get",
				"varicate",
				"urselves",
				"They don",
				"ntal. Th",
				"imental.",
				"ey don't",
				"e this o"
			]
		},
		{
			"args": {
				"CLICK": true
			},
			"calls": 23789,
			"base": "`LCLICK SECURED`",
			"fragments": [
				"stina",
				"revar",
				"o hav",
				"te and",
				"on't. ",
				"ntimen",
				"t in fi",
				"ricate ",
				"ne this",
				"l. They",
				"ghts an",
				"crastin",
				"and get",
				"varicate",
				"urselves",
				"They don",
				"ntal. Th",
				"imental.",
				"ey don't",
				"e this o"
			]
		}
	],
	"identified": [
		{
			"document": "MFT0X42_CLST0XE9_SECT0X63A2_FILE0X2194137C",
			"frags": [
				"rselv",
				"revar",
				"this o",
				"on't. ",
				"ne thi",
				"nd get",
				"t in fi",
				"crastin",
				"varicate",
				"ntal. Th",
				"imental."
			]
		}
	],
	"edit": 15,
	"updt": 1672649022413
}