{
	"_id": "unknown_lllgqb.bot_scam_do_not_run",
	"type": "fragment",
	"mode": "dead",
	"script": "unknown_lllgqb.bot_scam_do_not_run",
	"sector": "K_9453",
	"sec_level": 4,
	"date_added": 1621996832178,
	"last_scraped": 1622527976043,
	"script_log": [
		{
			"type": "added",
			"when": 1621996832178
		},
		{
			"type": "died",
			"when": 1624935876539
		},
		{
			"type": "died",
			"when": 1625436508927
		}
	],
	"retry_args": [
		{
			"CLICK": true
		}
	],
	"scrape_ct": 16,
	"next_scrape": 1622571004732,
	"category": "clicker",
	"last_update": 1622527976043,
	"output": [
		{
			"args": {},
			"calls": 22831,
			"base": "~~ `NCLICKER` `hGENERIC` `JRUSH` `HEX` `IPLUS` `DGAMMA` ~~\n\n`NCLICK` FOR `ICLICKS`\n`NCLICK` FOR `DGLORY`",
			"fragments": [
				"ts gr",
				"miyawa",
				"bal | ",
				"roducti",
				": Iona ",
				"-global",
				" | USER",
				" | SUBJ",
				"SUBJ: In",
				"ki comco"
			],
			"hits": [
				{
					"document": "MFT0XF4_CLST0XCC_SECT0X7BE4_FILE0XE2A8BDD4",
					"frags": [
						"ts gr",
						"miyawa",
						"bal | ",
						"roducti",
						": Iona ",
						"-global",
						" | USER",
						" | SUBJ",
						"SUBJ: In",
						"ki comco"
					]
				}
			]
		},
		{
			"args": {
				"click": true
			},
			"calls": 17418,
			"base": "I CANT HEAR YOU! `NCLICK` HARDER",
			"fragments": [
				"ts gr",
				"miyawa",
				"bal | ",
				"roducti",
				": Iona ",
				"-global",
				" | USER",
				" | SUBJ",
				"SUBJ: In",
				"ki comco"
			]
		}
	],
	"identified": [
		{
			"document": "MFT0XF4_CLST0XCC_SECT0X7BE4_FILE0XE2A8BDD4",
			"frags": [
				"ts gr",
				"miyawa",
				"bal | ",
				"roducti",
				": Iona ",
				"-global",
				" | USER",
				" | SUBJ",
				"SUBJ: In",
				"ki comco"
			]
		}
	],
	"updt": 1624935997857,
	"edit": 4
}