{
	"_id": "unknown_cspw88.tail",
	"type": "fragment",
	"mode": "dead",
	"script": "unknown_cspw88.tail",
	"sector": "K_2160",
	"sec_level": 4,
	"date_added": 1643336543909,
	"last_scraped": 1643336630456,
	"script_log": [
		{
			"type": "added",
			"when": 1643336543909
		},
		{
			"type": "died",
			"when": 1650029086563
		}
	],
	"retry_args": [
		{
			"do": "LOSE"
		}
	],
	"scrape_ct": 20,
	"next_scrape": 1643427357147,
	"category": "risk_factor",
	"last_update": 1643336630456,
	"output": [
		{
			"args": {},
			"calls": 1003,
			"base": "YOU COULD WIN 2GC with do:\"win\"\n\nOR\n\nYOU COULD `VLOSE`",
			"fragments": [
				"s inf",
				"finite",
				"could ",
				"nce is ",
				"I, at t",
				" That's",
				"? ## Tha",
				" AI, at "
			]
		},
		{
			"args": {
				"do": "win"
			},
			"calls": 106,
			"base": "YOU WON 2GC\n...if i could afford to pay out.",
			"fragments": [
				"s inf",
				"finite",
				"could ",
				"nce is ",
				"I, at t",
				" That's",
				"? ## Tha",
				" AI, at "
			]
		}
	],
	"updt": 1643336844621,
	"edit": 2,
	"cannot_identify": true
}