{
	"_id": "unknown_c41mlt.turing",
	"type": "fragment",
	"mode": "dead",
	"script": "unknown_c41mlt.turing",
	"sector": "K_7947",
	"sec_level": 4,
	"date_added": 1641555286856,
	"last_scraped": 1641555392622,
	"script_log": [
		{
			"type": "added",
			"when": 1641555286856
		},
		{
			"type": "died",
			"when": 1650171038913
		}
	],
	"scrape_ct": 17,
	"next_scrape": 1641555452622,
	"category": "fishie_tank",
	"last_update": 1641555392622,
	"output": [
		{
			"args": {},
			"calls": 3296,
			"base": "Some fishies are in the tank. They are swimming. and hungry?\ndo:\"feed\" | do:\"clean\"",
			"fragments": [
				"f know",
				"e Town",
				"truly m",
				"ie Buil",
				"wn That ",
				"e benefi",
				" is when"
			],
			"hits": [
				{
					"document": "MFT0X3E_CLST0X4A_SECT0X7052_FILE0X42B80721",
					"frags": [
						"f know",
						"e Town",
						"truly m",
						"ie Buil",
						"wn That ",
						"e benefi",
						" is when"
					]
				}
			]
		},
		{
			"args": {
				"do": "feed"
			},
			"calls": 1071,
			"base": [
				"Fishies are happy.",
				"actuly they look fine",
				"they are still hungry?",
				"they don't look so good"
			],
			"fragments": [
				"f know",
				"e Town",
				"truly m",
				"ie Buil",
				"wn That ",
				"e benefi",
				" is when"
			]
		},
		{
			"args": {
				"do": "clean"
			},
			"calls": 13284,
			"base": "Fishies are happy. Algea eaters are displeased.",
			"fragments": [
				"f know",
				"e Town",
				"truly m",
				"ie Buil",
				"wn That ",
				"e benefi",
				" is when"
			]
		}
	],
	"identified": [
		{
			"document": "MFT0X3E_CLST0X4A_SECT0X7052_FILE0X42B80721",
			"frags": [
				"f know",
				"e Town",
				"truly m",
				"ie Buil",
				"wn That ",
				"e benefi",
				" is when"
			]
		}
	],
	"updt": 1641555472240,
	"edit": 1
}