{
	"_id": "unknown_rpojwp.pub_4rjrua",
	"type": "fragment",
	"mode": "fresh",
	"script": "unknown_rpojwp.pub_4rjrua",
	"sector": "VNP_5814",
	"sec_level": 4,
	"date_added": 1641282439734,
	"last_scraped": 1641284003527,
	"script_log": [
		{
			"type": "added",
			"when": 1641282439734
		}
	],
	"updt": 1641282471312,
	"edit": 1,
	"scrape_ct": 19,
	"next_scrape": 1641284063527,
	"category": "dice_roller",
	"last_update": 1641284003527,
	"output": [
		{
			"args": {},
			"calls": 5954,
			"base": "Roll the dice!(tm)\n\nbeat the house's roll to win! {roll:true}",
			"fragments": [
				"u are",
				"attack",
				"are th",
				" attac",
				"nder,\\n",
				"m the a",
				"efender",
				"cker\\n20",
				"87 I am "
			],
			"hits": [
				{
					"document": "MFT0XBF_CLST0X7A_SECT0XF227_FILE0X2BC7D171",
					"frags": [
						"u are",
						"attack",
						"are th",
						" attac",
						"nder,\\n",
						"m the a",
						"efender",
						"cker\\n20",
						"87 I am "
					]
				}
			]
		}
	],
	"identified": [
		{
			"document": "MFT0XBF_CLST0X7A_SECT0XF227_FILE0X2BC7D171",
			"frags": [
				"u are",
				"attack",
				"are th",
				" attac",
				"nder,\\n",
				"m the a",
				"efender",
				"cker\\n20",
				"87 I am "
			]
		}
	]
}